faraday_plugins/__init__.py
faraday_plugins/__main__.py
faraday_plugins/commands.py
faraday_plugins/plugins/__init__.py
faraday_plugins/plugins/manager.py
faraday_plugins/plugins/plugin.py
faraday_plugins/plugins/plugins_utils.py
faraday_plugins/plugins/port_mapper.txt
faraday_plugins/plugins/repo/__init__.py
faraday_plugins/plugins/repo/acunetix/DTO.py
faraday_plugins/plugins/repo/acunetix/__init__.py
faraday_plugins/plugins/repo/acunetix/plugin.py
faraday_plugins/plugins/repo/acunetix360/DTO.py
faraday_plugins/plugins/repo/acunetix360/__init__.py
faraday_plugins/plugins/repo/acunetix360/plugin.py
faraday_plugins/plugins/repo/acunetix_json/DTO.py
faraday_plugins/plugins/repo/acunetix_json/__init__.py
faraday_plugins/plugins/repo/acunetix_json/plugin.py
faraday_plugins/plugins/repo/amap/__init__.py
faraday_plugins/plugins/repo/amap/plugin.py
faraday_plugins/plugins/repo/appscan/__init__.py
faraday_plugins/plugins/repo/appscan/plugin.py
faraday_plugins/plugins/repo/appscan_csv/__init__.py
faraday_plugins/plugins/repo/appscan_csv/plugin.py
faraday_plugins/plugins/repo/appspider/__init__.py
faraday_plugins/plugins/repo/appspider/plugin.py
faraday_plugins/plugins/repo/arachni/__init__.py
faraday_plugins/plugins/repo/arachni/plugin.py
faraday_plugins/plugins/repo/arp_scan/__init__.py
faraday_plugins/plugins/repo/arp_scan/plugin.py
faraday_plugins/plugins/repo/aws_inspector/__init__.py
faraday_plugins/plugins/repo/aws_inspector/plugin.py
faraday_plugins/plugins/repo/bandit/__init__.py
faraday_plugins/plugins/repo/bandit/plugin.py
faraday_plugins/plugins/repo/beef/__init__.py
faraday_plugins/plugins/repo/beef/plugin.py
faraday_plugins/plugins/repo/brutexss/__init__.py
faraday_plugins/plugins/repo/brutexss/plugin.py
faraday_plugins/plugins/repo/burp/__init__.py
faraday_plugins/plugins/repo/burp/plugin.py
faraday_plugins/plugins/repo/checkmarx/__init__.py
faraday_plugins/plugins/repo/checkmarx/plugin.py
faraday_plugins/plugins/repo/cis/__init__.py
faraday_plugins-1.27.2.dist-info/licenses/COPYING
faraday_plugins-1.27.2.dist-info/METADATA
faraday_plugins-1.27.2.dist-info/WHEEL
faraday_plugins-1.27.2.dist-info/entry_points.txt
faraday_plugins-1.27.2.dist-info/top_level.txt
faraday_plugins-1.27.2.dist-info/RECORD
