Metadata-Version: 2.4
Name: faraday_plugins
Version: 1.27.2
Summary: Faraday plugins package
Home-page: 
Author: Faradaysec
Author-email: devel@faradaysec.com
License: GNU General Public License v3
License-File: COPYING
Requires-Dist: Click
Requires-Dist: simplejson
Requires-Dist: requests
Requires-Dist: lxml
Requires-Dist: html2text
Requires-Dist: beautifulsoup4
Requires-Dist: pytz
Requires-Dist: python-dateutil
Requires-Dist: colorama
Requires-Dist: tabulate
Requires-Dist: packaging
Requires-Dist: markdown
Requires-Dist: tldextract
Requires-Dist: pandas
Dynamic: author
Dynamic: author-email
Dynamic: description
Dynamic: description-content-type
Dynamic: license
Dynamic: license-file
Dynamic: requires-dist
Dynamic: summary
